devcord.py
app/__init__.py
app/__main__.py
app/__version__.py
app/application.py
app/config.py
app/console.py
app/console_helper.py
app/constants.py
app/database.py
app/helper.py
app/migrations.py
app/tempCodeRunnerFile.py
app/utility.py
app/db_upgrade/__init__.py
app/db_upgrade/upgrades.py
app/sessions/__init__.py
app/sessions/linux.py
jira/__init__.py
jira/application.py
jira/console.py
jira/database.py
tests/__init__.py
tests/test_application_layer.py
tests/test_utility.py
special_octo_robot-1.0.1.dist-info/LICENSE
special_octo_robot-1.0.1.dist-info/METADATA
special_octo_robot-1.0.1.dist-info/WHEEL
special_octo_robot-1.0.1.dist-info/entry_points.txt
special_octo_robot-1.0.1.dist-info/top_level.txt
special_octo_robot-1.0.1.dist-info/RECORD
