Metadata-Version: 2.1
Name: special-octo-robot
Version: 1.0.1
Summary: Creating my own version of what a CLI Task manager and To-do-list would look like
Home-page: https://github.com/geekNero/special-octo-robot.git
Author: Jahan Chaware
Author-email: sg550js@gmail.com
License: GNU GENERAL PUBLIC LICENSE
Platform: Windows
Platform: MacOS X
Platform: Linux
Classifier: Programming Language :: Python :: 3
Classifier: Operating System :: MacOS :: MacOS X
Classifier: Operating System :: Microsoft :: Windows
Classifier: Operating System :: POSIX :: Linux
Requires-Python: >=3.10
License-File: LICENSE
Requires-Dist: click >=8.0.1
Requires-Dist: ewmh >=0.1.6
Requires-Dist: keyring >=25.0.0
Requires-Dist: packaging >=24.0
Requires-Dist: PrettyPrintTree >=2.0.1
Requires-Dist: prompt-toolkit >=3.0.43
Requires-Dist: requests >=2.31.0
Requires-Dist: rich >=13.7.0
Requires-Dist: xlib >=0.21
